.gitignore
LICENSE
README.rst
manage.py
requirements.txt
setup.py
ab/__init__.py
ab/admin.py
ab/forms.py
ab/interface.py
ab/models.py
ab/tests.py
ab/urls.py
ab/views.py
accounts/__init__.py
accounts/forms.py
accounts/models.py
accounts/tests.py
accounts/urls.py
accounts/views.py
admin_ext/__init__.py
admin_ext/models.py
admin_ext/tests.py
admin_ext/views.py
bin/clutch-all
bin/clutch-config
bin/clutch-rpc
bin/clutch-test
bin/clutch-tunnel
bin/clutch-web
bin/dev
clutch/__init__.py
clutch/settings.py
clutch/urls.py
clutch/views.py
clutch/wsgi.py
clutch/media/__delete_me__.txt
clutch/media/static/admin/css/base.css
clutch/media/static/admin/css/changelists.css
clutch/media/static/admin/css/dashboard.css
clutch/media/static/admin/css/forms.css
clutch/media/static/admin/css/ie.css
clutch/media/static/admin/css/login.css
clutch/media/static/admin/css/rtl.css
clutch/media/static/admin/css/widgets.css
clutch/media/static/admin/img/changelist-bg.gif
clutch/media/static/admin/img/changelist-bg_rtl.gif
clutch/media/static/admin/img/chooser-bg.gif
clutch/media/static/admin/img/chooser_stacked-bg.gif
clutch/media/static/admin/img/default-bg-reverse.gif
clutch/media/static/admin/img/default-bg.gif
clutch/media/static/admin/img/deleted-overlay.gif
clutch/media/static/admin/img/icon-no.gif
clutch/media/static/admin/img/icon-unknown.gif
clutch/media/static/admin/img/icon-yes.gif
clutch/media/static/admin/img/icon_addlink.gif
clutch/media/static/admin/img/icon_alert.gif
clutch/media/static/admin/img/icon_calendar.gif
clutch/media/static/admin/img/icon_changelink.gif
clutch/media/static/admin/img/icon_clock.gif
clutch/media/static/admin/img/icon_deletelink.gif
clutch/media/static/admin/img/icon_error.gif
clutch/media/static/admin/img/icon_searchbox.png
clutch/media/static/admin/img/icon_success.gif
clutch/media/static/admin/img/inline-delete-8bit.png
clutch/media/static/admin/img/inline-delete.png
clutch/media/static/admin/img/inline-restore-8bit.png
clutchserver.egg-info/PKG-INFO
clutchserver.egg-info/SOURCES.txt
clutchserver.egg-info/dependency_links.txt
clutchserver.egg-info/not-zip-safe
clutchserver.egg-info/requires.txt
clutchserver.egg-info/top_level.txt
