Metadata-Version: 1.0
Name: clutchserver
Version: 0.1.0
Summary: The server component for Clutch framework and Cluth A/B Testing.
Home-page: UNKNOWN
Author: Eric Florenzano
Author-email: eflorenzano@twitter.com
License: UNKNOWN
Platform: UNKNOWN
